README.md
setup.py
sysops/__init__.py
sysops.egg-info/PKG-INFO
sysops.egg-info/SOURCES.txt
sysops.egg-info/dependency_links.txt
sysops.egg-info/requires.txt
sysops.egg-info/top_level.txt
sysops.egg-info/zip-safe
sysops/config/__init__.py
sysops/config/manager.py
sysops/config/util.py
sysops/config/linux/__init__.py
sysops/config/linux/apt.py
sysops/config/linux/debian.py
sysops/config/linux/deblike.py
sysops/config/linux/linux.py
sysops/config/linux/openwrt.py
sysops/config/linux/ubuntu.py
sysops/tools/__init__.py
sysops/tools/docker.py
sysops/tools/generator.py
sysops/tools/pwgen.py
sysops/tools/netcalc/__init__.py
sysops/tools/netcalc/test.py