Metadata-Version: 1.1
Name: sysops
Version: 0.0.10
Summary: just for test
Home-page: UNKNOWN
Author: xxy1991
Author-email: UNKNOWN
License: UNKNOWN
Platform: UNKNOWN
Classifier: Programming Language :: Python
